{
  "color": "#f800f8",
  "containers": [
    {
      "filled": [
        "immersiveengineering:potion_bucket"
      ],
      "empty": "minecraft:bucket",
      "capacity": 4
    },
    {
      "filled": [
        "minecraft:potion",
        "minecraft:splash_potion",
        "minecraft:lingering_potion"
      ],
      "empty": "minecraft:glass_bottle",
      "capacity": 1
    },
    {
      "filled": [
        "minecraft:lingering_potion"
      ],
      "empty": "inspirations:lingering_bottle",
      "capacity": 1
    },
    {
      "filled": [
        "minecraft:splash_potion"
      ],
      "empty": "inspirations:splash_bottle",
      "capacity": 1
    }
  ],
  "equivalent_fluids": [
    "create:potion",
    "cofh_core:potion",
    "immersiveengineering:potion"
  ],
  "flowing_texture": "moonlight:soft_fluids/potion_flow",
  "food": {
    "divider": 1,
    "item": "minecraft:potion"
  },
  "preserved_tags_from_item": [
    "Potion",
    "Bottle",
    "CustomPotionEffects"
  ],
  "still_texture": "moonlight:soft_fluids/potion_still",
  "translation_key": "item.minecraft.potion",
  "use_texture_from": "create:potion"
}

